.gitignore
LICENSE
MANIFEST.in
README
ez_setup.py
ez_setup.pyc
setup.py
django-jobs/__init__.py
django-jobs/admin.py
django-jobs/forms.py
django-jobs/models.py
django-jobs/urls.py
django-jobs/views.py
django-jobs/templates/jobs/about.html
django-jobs/templates/jobs/adddev.html
django-jobs/templates/jobs/addjob.html
django-jobs/templates/jobs/base.html
django-jobs/templates/jobs/developer.html
django-jobs/templates/jobs/developers.html
django-jobs/templates/jobs/editdev.html
django-jobs/templates/jobs/editdevdone.html
django-jobs/templates/jobs/editjob.html
django-jobs/templates/jobs/job.html
django-jobs/templates/jobs/jobs.html
django_jobs.egg-info/PKG-INFO
django_jobs.egg-info/SOURCES.txt
django_jobs.egg-info/dependency_links.txt
django_jobs.egg-info/not-zip-safe
django_jobs.egg-info/top_level.txt
project/__init__.py
project/manage.py
project/settings.py
project/urls.py
project/jobs/__init__.py
project/jobs/admin.py
project/jobs/forms.py
project/jobs/models.py
project/jobs/urls.py
project/jobs/views.py